MANIFEST.in
setup.py
docs/HISTORY.txt
src/menhir/__init__.py
src/menhir.contenttype.photoalbum.egg-info/PKG-INFO
src/menhir.contenttype.photoalbum.egg-info/SOURCES.txt
src/menhir.contenttype.photoalbum.egg-info/dependency_links.txt
src/menhir.contenttype.photoalbum.egg-info/entry_points.txt
src/menhir.contenttype.photoalbum.egg-info/namespace_packages.txt
src/menhir.contenttype.photoalbum.egg-info/not-zip-safe
src/menhir.contenttype.photoalbum.egg-info/requires.txt
src/menhir.contenttype.photoalbum.egg-info/top_level.txt
src/menhir/contenttype/__init__.py
src/menhir/contenttype/photoalbum/README.txt
src/menhir/contenttype/photoalbum/__init__.py
src/menhir/contenttype/photoalbum/album.py
src/menhir/contenttype/photoalbum/configure.zcml
src/menhir/contenttype/photoalbum/libraries.py
src/menhir/contenttype/photoalbum/views.py
src/menhir/contenttype/photoalbum/locales/en/LC_MESSAGES/menhir.contenttype.photoalbum.mo
src/menhir/contenttype/photoalbum/locales/en/LC_MESSAGES/menhir.contenttype.photoalbum.po
src/menhir/contenttype/photoalbum/locales/fr/LC_MESSAGES/menhir.contenttype.photoalbum.mo
src/menhir/contenttype/photoalbum/locales/fr/LC_MESSAGES/menhir.contenttype.photoalbum.po
src/menhir/contenttype/photoalbum/resources/album.png
src/menhir/contenttype/photoalbum/resources/gallery.css
src/menhir/contenttype/photoalbum/resources/gallery.js
src/menhir/contenttype/photoalbum/tests/__init__.py
src/menhir/contenttype/photoalbum/tests/dolmen-test-site.png
src/menhir/contenttype/photoalbum/tests/dolmen.png
src/menhir/contenttype/photoalbum/tests/ftesting.zcml
src/menhir/contenttype/photoalbum/tests/test_general.py
src/menhir/contenttype/photoalbum/views_templates/animated.cpt
src/menhir/contenttype/photoalbum/views_templates/simple.cpt