Metadata-Version: 1.0
Name: menhir.contenttype.photoalbum
Version: 0.3
Summary: Dolmen contenttype extension : photoalbum
Home-page: http://www.dolmen-project.org
Author: Souheil Chelfouh
Author-email: trollfot@gmail.com
License: GPL
Keywords: Grok Zope3 CMS Dolmen
Platform: Any
Classifier: Environment :: Web Environment
Classifier: Intended Audience :: Other Audience
Classifier: License :: OSI Approved :: GNU General Public License (GPL)
Classifier: Operating System :: OS Independent
Classifier: Programming Language :: Python
